LICENSE
MANIFEST.in
README.md
setup.py
dsm_django_socialauth.egg-info/PKG-INFO
dsm_django_socialauth.egg-info/SOURCES.txt
dsm_django_socialauth.egg-info/dependency_links.txt
dsm_django_socialauth.egg-info/requires.txt
dsm_django_socialauth.egg-info/top_level.txt
dsmauth/__init__.py
dsmauth/admin.py
dsmauth/api.py
dsmauth/backend.py
dsmauth/complete.py
dsmauth/middleware.py
dsmauth/models.py
dsmauth/urls.py
dsmauth/utils.py
dsmauth/views.py
dsmauth/migrations/0001_initial.py
dsmauth/migrations/0002_accesslog.py
dsmauth/migrations/__init__.py
dsmauth/templates/admin/base.html
dsmauth/templates/admin/base_site.html
dsmauth/templates/admin/custom-index.html
dsmauth/templates/admin/custom-login.html