Metadata-Version: 2.2
Name: dsm-django-socialauth
Version: 1.0.39
Summary: A simple way to use Custom authentication in django application. for dsm
Home-page: https://gitlab.com/public-project2/dsm-django-oauth
Author: DigitalStoreMesh Co.,Ltd
Author-email: contact@storemesh.com
License: MIT License
Classifier: Environment :: Web Environment
Classifier: Framework :: Django
Classifier: Framework :: Django :: 4.0
Classifier: Intended Audience :: Developers
Classifier: License :: OSI Approved :: MIT License
Classifier: Operating System :: OS Independent
Classifier: Programming Language :: Python
Classifier: Programming Language :: Python :: 3.7
Classifier: Programming Language :: Python :: 3.8
Classifier: Topic :: Internet :: WWW/HTTP
Classifier: Topic :: Internet :: WWW/HTTP :: Dynamic Content
License-File: LICENSE
Requires-Dist: social-auth-app-django
Requires-Dist: djangorestframework-simplejwt
Requires-Dist: Pillow
Dynamic: author
Dynamic: author-email
Dynamic: classifier
Dynamic: description
Dynamic: description-content-type
Dynamic: home-page
Dynamic: license
Dynamic: requires-dist
Dynamic: summary
